PyNOMAD-0.1.7.post1.dist-info/DESCRIPTION.rst
PyNOMAD-0.1.7.post1.dist-info/METADATA
PyNOMAD-0.1.7.post1.dist-info/RECORD
PyNOMAD-0.1.7.post1.dist-info/WHEEL
PyNOMAD-0.1.7.post1.dist-info/metadata.json
PyNOMAD-0.1.7.post1.dist-info/top_level.txt
nomad/__about__.py
nomad/__init__.py
nomad/confirm_range_of_ra_swatches.py
nomad/nomad.py
nomad/nomad_test.py
