Metadata-Version: 2.0
Name: PyNOMAD
Version: 0.1.7.post1
Summary: Routines for accessing a self-hosted local copy of the USNO NOMAD stellar catalog
Home-page: https://github.com/henryroe/PyNOMAD
Author: Henry Roe
Author-email: hroe@hroe.me
License: MIT License
Keywords: NOMAD catalog
Platform: UNKNOWN
Classifier: Development Status :: 4 - Beta
Classifier: Intended Audience :: Science/Research
Classifier: Topic :: Scientific/Engineering :: Astronomy
Classifier: License :: OSI Approved :: MIT License
Classifier: Programming Language :: Python :: 2
Classifier: Programming Language :: Python :: 2.7
Requires-Dist: astropy-helpers (>=1.0.0)
Requires-Dist: pandas (>=0.15.0)
